ropey-0.0.4_alpha.dist-info/METADATA
ropey-0.0.4_alpha.dist-info/WHEEL
ropey/__init__.py
ropey/__init__.pyi
ropey/py.typed
ropey/ropey.cpython-38-darwin.so
ropey-0.0.4_alpha.dist-info/RECORD
