Metadata-Version: 2.1
Name: ropey
Version: 0.0.4_alpha
Classifier: Programming Language :: Rust
Classifier: Programming Language :: Python :: Implementation :: CPython
Classifier: Programming Language :: Python :: Implementation :: PyPy
Summary: Python bindings for Rust's Ropey library.
Author: Jérome Eertmans <jeertmans@icloud.com>
Author-email: Jérome Eertmans <jeertmans@icloud.com>
Maintainer-email: Jérome Eertmans <jeertmans@icloud.com>
License: 